pyProdigy/__init__.py
pyProdigy/_version.py
pyProdigy/dataset.py
pyProdigy/par_const.py
pyProdigy-0.0.0.dist-info/LICENSE
pyProdigy-0.0.0.dist-info/METADATA
pyProdigy-0.0.0.dist-info/WHEEL
pyProdigy-0.0.0.dist-info/top_level.txt
pyProdigy-0.0.0.dist-info/RECORD
