Metadata-Version: 2.1
Name: pyProdigy
Version: 0.0.0
Summary: Utilities and scripts for the Prodigy project.
Home-page: https://github.com/ltesti/pyProdigy
Author: Leonardo Testi
Author-email: ltesti120a@gmail.com
License: LGPLv3
Download-URL: https://github.com/ltesti/pyPro/archive/0.0.00.tar.gz
Keywords: science,astronomy,interferometry,ALMA
Platform: UNKNOWN
Classifier: Development Status :: 5 - Production/Stable
Classifier: Intended Audience :: Developers
Classifier: Intended Audience :: Science/Research
Classifier: Operating System :: OS Independent
Classifier: License :: OSI Approved :: GNU Lesser General Public License v3 (LGPLv3)
Classifier: Programming Language :: Python :: 2
Classifier: Programming Language :: Python :: 3
Requires-Dist: numpy (>=1.9)
Requires-Dist: matplotlib
